tona_ai/__init__.py
tona_ai/_version.py
tona_ai/core/__init__.py
tona_ai/core/activation_function.py
tona_ai/core/activation_functions.py
tona_ai/core/layer.py
tona_ai/core/layer_type.py
tona_ai/core/neural_network.py
tona_ai/core/neuron_synapse.py
tona_ai/neat/__init__.py
tona_ai/neat/environment.py
tona_ai/neat/genome.py
tona_ai/neat/individual.py
tona_ai/neat/neat.py
tona_ai/neat/population.py
tona_ai-0.0.12.dist-info/AUTHORS.md
tona_ai-0.0.12.dist-info/LICENSE
tona_ai-0.0.12.dist-info/METADATA
tona_ai-0.0.12.dist-info/WHEEL
tona_ai-0.0.12.dist-info/top_level.txt
tona_ai-0.0.12.dist-info/RECORD
